[
  {
    "id": "combat_reflexes",
    "isAdvantage": true,
    "name": "Reflexos de Combate",

    "baseCost": 15,
    "costIsVariable": true,
    "variableCost": 10,

    "display": "Reflexos de Combate",

    "isAllowedLevel": true,
    "maxLevel": 3,

    "shortDescription": "Você reage mais rapidamente que pessoas normais.",
    "fullDescription": "Você reage mais rapidamente que pessoas normais.",

    "formula": null,
    "formulaDescription": null,

    "types": ["Physical", "Combat"],

    "requirements": [
      {
        "attribute": "DX",
        "operator": "GTE",
        "value": 2,
        "display": "Destreza +2"
      }
    ],

    "restrictions": [
      {
        "restrictedId": "unconscious",
        "display": "Não pode ser usado enquanto estiver inconsciente"
      }
    ],

    "modifiers": [
      {
        "attribute": "DX",
        "operator": "ADD",
        "value": 1,
        "display": "+1 Destreza"
      }
    ],

    "effects": [
      {
        "name": "Reflexos Rápidos",
        "effectType": "initiative_bonus",
        "display": "+2 na iniciativa"
      }
    ]
  },

  {
    "id": "acute_vision",
    "isAdvantage": true,
    "name": "Visão Aguçada",

    "baseCost": 5,
    "costIsVariable": true,
    "variableCost": 5,

    "display": "Visão Aguçada",

    "isAllowedLevel": true,
    "maxLevel": 4,

    "shortDescription": "Seus olhos enxergam com mais nitidez que o normal.",
    "fullDescription": "Seus olhos enxergam com mais nitidez que o normal.",

    "formula": null,
    "formulaDescription": null,

    "types": ["Physical"],

    "requirements": [],

    "restrictions": [],

    "modifiers": [
      {
        "attribute": "PER",
        "operator": "ADD",
        "value": 2,
        "display": "+2 Percepção (visão)"
      }
    ],
    "effects": []
  },

  {
    "id": "blind",
    "isAdvantage": false,
    "name": "Cego",

    "baseCost": -50,
    "costIsVariable": false,
    "variableCost": 0,

    "display": "Cego",

    "isAllowedLevel": false,
    "maxLevel": null,

    "shortDescription": "Você não pode enxergar.",
    "fullDescription": "Você não pode enxergar. Todos os testes que dependam de visão falham automaticamente.",

    "formula": null,
    "formulaDescription": null,

    "types": ["Physical"],

    "requirements": [],

    "restrictions": [
      {
        "restrictedId": "acute_vision",
        "display": "Incompatível com Visão Aguçada"
      }
    ],

    "modifiers": [],

    "effects": [
      {
        "name": "Cegueira Total",
        "effectType": "vision_disabled",
        "display": "Não pode usar habilidades que exijam visão"
      }
    ]
  }
]
